<?xml version="1.0" encoding="utf-8"?>
<!DOCTYPE hibernate-mapping PUBLIC "-//Hibernate/Hibernate Mapping DTD 3.0//EN"
"http://www.hibernate.org/dtd/hibernate-mapping-3.0.dtd">
<!-- 
    Mapping file autogenerated by MyEclipse Persistence Tools
-->
<hibernate-mapping>
    <class name="com.bs.entity.Formula" table="formula" catalog="database">
        <id name="number" type="java.lang.Integer">
            <column name="Number" />
            <generator class="native"></generator>
        </id>
        <many-to-one name="feed" class="com.bs.entity.Feed" insert="false" update="false" lazy="false">
            <column name="FeedId"/>
        </many-to-one>
        <property name="component" type="java.lang.String">
            <column name="component" length="20" />
        </property>
        <property name="content" type="java.lang.Double">
            <column name="content" precision="22" scale="0" />
        </property>
        <property name="formulaId" type="java.lang.Integer">
            <column name="FormulaId" not-null="true" />
        </property>
    </class>
</hibernate-mapping>
